pypkgs_elina/__init__.py
pypkgs_elina/pypkgs_elina.py
pypkgs_elina-0.1.0.dist-info/LICENSE
pypkgs_elina-0.1.0.dist-info/WHEEL
pypkgs_elina-0.1.0.dist-info/METADATA
pypkgs_elina-0.1.0.dist-info/RECORD
