Metadata-Version: 2.1
Name: pypkgs-elina
Version: 0.1.0
Summary: "Python package that eases the pain of concatenating Pandas categoricals!"
License: "MIT"
Author: Ling Lin
Author-email: elinall626@gmail.com
Requires-Python: >=3.8,<4.0
Classifier: License :: Other/Proprietary License
Classifier: Programming Language :: Python :: 3
Classifier: Programming Language :: Python :: 3.8
Classifier: Programming Language :: Python :: 3.9
Requires-Dist: pandas (>=1.2.2,<2.0.0)
